gauze/__init__.py
gauze/_version.py
gauze/simple.py
gauze-0.1.0.dist-info/LICENSE
gauze-0.1.0.dist-info/METADATA
gauze-0.1.0.dist-info/WHEEL
gauze-0.1.0.dist-info/top_level.txt
gauze-0.1.0.dist-info/RECORD
